TheiaMCR/TheiaMCR.py
TheiaMCR/__init__.py
TheiaMCR/errList.py
TheiaMCR/rotatingLogFiles.py
theiamcr-3.4.0.dist-info/licenses/LICENSE
theiamcr-3.4.0.dist-info/METADATA
theiamcr-3.4.0.dist-info/WHEEL
theiamcr-3.4.0.dist-info/top_level.txt
theiamcr-3.4.0.dist-info/RECORD
