Metadata-Version: 2.4
Name: TheiaMCR
Version: 3.4.0
Summary: Theia MCR motor control functions
Author-email: Mark Peterson <mpeterson@theiatech.com>
License-Expression: BSD-3-Clause
Project-URL: Homepage, https://github.com/cliquot22/TheiaMCR
Project-URL: Documentation, https://github.com/cliquot22/TheiaMCR/wiki
Project-URL: Issues, https://github.com/cliquot22/TheiaMCR/issues
Classifier: Development Status :: 5 - Production/Stable
Classifier: Intended Audience :: Science/Research
Classifier: Intended Audience :: Manufacturing
Classifier: Operating System :: Microsoft :: Windows
Classifier: Programming Language :: Python :: 3
Classifier: Natural Language :: English
Requires-Python: >=3.10
License-File: LICENSE
Requires-Dist: pyserial
Requires-Dist: logging
Dynamic: license-file
